pytest_variables/__init__.py
pytest_variables/__version.py
pytest_variables/errors.py
pytest_variables/plugin.py
pytest_variables-3.0.0.dist-info/METADATA
pytest_variables-3.0.0.dist-info/WHEEL
pytest_variables-3.0.0.dist-info/entry_points.txt
pytest_variables-3.0.0.dist-info/licenses/LICENSE
pytest_variables-3.0.0.dist-info/RECORD
