Metadata-Version: 2.1
Name: pytest-variables
Version: 3.0.0
Summary: pytest plugin for providing variables to tests/fixtures
Project-URL: Homepage, https://github.com/pytest-dev/pytest-variables
Project-URL: Tracker, https://github.com/pytest-dev/pytest-variables/issues
Project-URL: Source, https://github.com/pytest-dev/pytest-variables
Author-email: Dave Hunt <dhunt@mozilla.com>, Jim Brannlund <jimbrannlund@fastmail.com>
License-Expression: MPL-2.0
License-File: LICENSE
Keywords: json,pytest,variables
Classifier: Development Status :: 5 - Production/Stable
Classifier: Framework :: Pytest
Classifier: Intended Audience :: Developers
Classifier: License :: OSI Approved :: MIT License
Classifier: Natural Language :: English
Classifier: Operating System :: MacOS :: MacOS X
Classifier: Operating System :: Microsoft :: Windows
Classifier: Operating System :: POSIX
Classifier: Programming Language :: Python :: 3.7
Classifier: Programming Language :: Python :: 3.8
Classifier: Programming Language :: Python :: 3.9
Classifier: Programming Language :: Python :: 3.10
Classifier: Programming Language :: Python :: 3.11
Classifier: Programming Language :: Python :: Implementation :: CPython
Classifier: Programming Language :: Python :: Implementation :: PyPy
Classifier: Topic :: Software Development :: Quality Assurance
Classifier: Topic :: Software Development :: Testing
Classifier: Topic :: Utilities
Requires-Python: >=3.7
Requires-Dist: pytest>=7.0.0
Provides-Extra: hjson
Requires-Dist: hjson; extra == 'hjson'
Provides-Extra: test
Requires-Dist: black>=22.1.0; extra == 'test'
Requires-Dist: flake8>=4.0.1; extra == 'test'
Requires-Dist: pre-commit>=2.17.0; extra == 'test'
Requires-Dist: tox>=3.24.5; extra == 'test'
Provides-Extra: toml
Requires-Dist: toml; extra == 'toml'
Provides-Extra: yaml
Requires-Dist: pyyaml; extra == 'yaml'
